aws_satella/__init__.py
aws_satella/exporter.py
aws_satella/contrib/__init__.py
aws_satella/contrib/django.py
aws_satella-2.4.dist-info/LICENSE
aws_satella-2.4.dist-info/METADATA
aws_satella-2.4.dist-info/WHEEL
aws_satella-2.4.dist-info/top_level.txt
aws_satella-2.4.dist-info/RECORD
