Metadata-Version: 2.1
Name: aws-satella
Version: 2.4
Summary: Integration of Satella's metrics with AWS CloudWatch
Home-page: https://github.com/piotrmaslanka/aws-satella
Author: Piotr Maślanka
Author-email: pmaslanka@smok.co
License: UNKNOWN
Project-URL: Code, https://github.com/piotrmaslanka/aws-satella
Project-URL: Issue tracker, https://github.com/piotrmaslanka/aws-satella/issues
Keywords: metrics,aws,satella
Platform: UNKNOWN
Classifier: Programming Language :: Python
Classifier: Programming Language :: Python :: 3.5
Classifier: Programming Language :: Python :: 3.6
Classifier: Programming Language :: Python :: 3.7
Classifier: Programming Language :: Python :: 3.8
Classifier: Programming Language :: Python :: 3.9
Classifier: Programming Language :: Python :: Implementation :: CPython
Classifier: Programming Language :: Python :: Implementation :: PyPy
Classifier: Operating System :: OS Independent
Classifier: Development Status :: 5 - Production/Stable
Classifier: License :: OSI Approved :: MIT License
Classifier: Topic :: Software Development :: Libraries
Requires-Python: !=2.7.*,!=3.0.*,!=3.1.*,!=3.2.*,!=3.3.*,!=3.4.*
Requires-Dist: satella
Requires-Dist: boto3
Requires-Dist: botocore
